{
    "chart": {
        "data": [
            {
                "x": 1544450148624,
                "y": 2000,
                "label": null
            },
            {
                "x": 1544457253917,
                "y": 2000,
                "label": null
            },
            {
                "x": 1544464359210,
                "y": 2000,
                "label": null
            },
            {
                "x": 1544471464503,
                "y": 2000,
                "label": null
            },
            {
                "x": 1544478569796,
                "y": 2000,
                "label": null
            },
            {
                "x": 1544485675089,
                "y": 2000,
                "label": null
            },
            {
                "x": 1544492780382,
                "y": 2000,
                "label": null
            },
            {
                "x": 1544499885675,
                "y": 2000,
                "label": null
            },
            {
                "x": 1544506990968,
                "y": 2000,
                "label": null
            },
            {
                "x": 1544514096261,
                "y": 5000,
                "label": null
            },
            {
                "x": 1544521201554,
                "y": 5000,
                "label": null
            },
            {
                "x": 1544528306847,
                "y": 5000,
                "label": null
            },
            {
                "x": 1544535412140,
                "y": 20000,
                "label": null
            },
            {
                "x": 1544542517433,
                "y": 20000,
                "label": null
            },
            {
                "x": 1544549622726,
                "y": 20000,
                "label": null
            },
            {
                "x": 1544556728019,
                "y": 20000,
                "label": null
            },
            {
                "x": 1544563833312,
                "y": 20000,
                "label": null
            },
            {
                "x": 1544570938605,
                "y": 20000,
                "label": null
            },
            {
                "x": 1544578043898,
                "y": 20000,
                "label": null
            },
            {
                "x": 1544585149191,
                "y": 20000,
                "label": null
            },
            {
                "x": 1544592254484,
                "y": 20000,
                "label": null
            },
            {
                "x": 1544599359777,
                "y": 20000,
                "label": null
            },
            {
                "x": 1544606465070,
                "y": 20000,
                "label": null
            },
            {
                "x": 1544613570363,
                "y": 20000,
                "label": null
            },
            {
                "x": 1544620675656,
                "y": 36000,
                "label": null
            }
        ],
        "chartTypeHint": "line-chart",
        "dataTitle": "Compute Time Used",
        "dataTypes": ["datetime", "duration"]
    },
    "quota": null
}